pycmap/__init__.py
pycmap/annotatedHeatmap.py
pycmap/baseGraph.py
pycmap/clean.py
pycmap/cmap.py
pycmap/colorMaps.py
pycmap/common.py
pycmap/deepC.py
pycmap/export.py
pycmap/foliumHeat.py
pycmap/hist.py
pycmap/map.py
pycmap/match.py
pycmap/rest.py
pycmap/sample.py
pycmap/section.py
pycmap/supervised.py
pycmap/trend.py
pycmap/viz.py
pycmap/w3.py
pycmap-0.2.19.dist-info/LICENSE
pycmap-0.2.19.dist-info/METADATA
pycmap-0.2.19.dist-info/WHEEL
pycmap-0.2.19.dist-info/top_level.txt
pycmap-0.2.19.dist-info/RECORD
