Metadata-Version: 2.1
Name: pycmap
Version: 0.2.19
Summary: Simons CMAP API python client
Home-page: https://github.com/simonscmap/pycmap
Author: Mohammad D. Ashkezari
Author-email: mdehghan@uw.edu
Keywords: ocean oceanography data visualization satellite model in-situ remote sensing machine learning
Classifier: Development Status :: 3 - Alpha
Classifier: Intended Audience :: Science/Research
Classifier: License :: OSI Approved :: MIT License
Classifier: Programming Language :: Python :: 3.7
License-File: LICENSE
Requires-Dist: numpy
Requires-Dist: pandas
Requires-Dist: scipy
Requires-Dist: bokeh
Requires-Dist: matplotlib
Requires-Dist: cmocean
Requires-Dist: tqdm
Requires-Dist: folium
Requires-Dist: colorama
Requires-Dist: plotly
